<?xml version="1.0" ?>
<TLFDBLandmarks>
    <TLFLandmarkAttributes>
        <TLFLandmarkAttr ID="65FE75D4-B829-4117-8076-0A6D116F6EE5" ClassName="wing-1" Color="33023" />
        <TLFLandmarkAttr ID="AAF4E336-75AE-4802-BF5B-5A054968DC84" ClassName="wing-2" Color="16777215" />
        <TLFLandmarkAttr ID="DA50F8EA-E59A-480D-98F9-55710235D1B7" ClassName="wing-3" Color="65535" />
        <TLFLandmarkAttr ID="5F86768E-E0BA-45B2-BE5E-BB5A1F28C919" ClassName="wing-4" Color="16711935" />
        <TLFLandmarkAttr ID="B3CF6567-2FEA-4169-B9EA-229652889D69" ClassName="wing-5" Color="16776960" />
        <TLFLandmarkAttr ID="2C9C044F-73B6-4D31-B3B3-4645493B3745" ClassName="wing-6" Color="16711680" />
        <TLFLandmarkAttr ID="CD5DE575-CD69-4349-89E4-2DCEFC47930E" ClassName="wing-7" Color="65280" />
        <TLFLandmarkAttr ID="7BFF3331-C358-461B-968E-F8ABB18A4C97" ClassName="wing-8" Color="255" />
    </TLFLandmarkAttributes>
    <TLFLandmarkFiles>
        <TLFLandmarkFile FileName="PHO00001.JPG">
            <TLFLandmark ID="65FE75D4-B829-4117-8076-0A6D116F6EE5" X="31.458333" Y="32.222222" S="0.000000" />
            <TLFLandmark ID="AAF4E336-75AE-4802-BF5B-5A054968DC84" X="93.437500" Y="35.740741" S="1.000000" />
            <TLFLandmark ID="DA50F8EA-E59A-480D-98F9-55710235D1B7" X="58.333333" Y="35.185185" S="0.000000" />
            <TLFLandmark ID="5F86768E-E0BA-45B2-BE5E-BB5A1F28C919" X="37.343750" Y="23.796296" S="1.000000" />
            <TLFLandmark ID="B3CF6567-2FEA-4169-B9EA-229652889D69" X="58.541667" Y="54.074074" S="0.000000" />
            <TLFLandmark ID="2C9C044F-73B6-4D31-B3B3-4645493B3745" X="69.791667" Y="59.259259" S="0.000000" />
            <TLFLandmark ID="CD5DE575-CD69-4349-89E4-2DCEFC47930E" X="74.375000" Y="56.296296" S="0.000000" />
            <TLFLandmark ID="7BFF3331-C358-461B-968E-F8ABB18A4C97" X="59.375000" Y="78.148148" S="0.000000" />
        </TLFLandmarkFile>
        <TLFLandmarkFile FileName="PHO00002.JPG">
            <TLFLandmark ID="65FE75D4-B829-4117-8076-0A6D116F6EE5" X="31.458333" Y="32.222222" S="0.000000" />
            <TLFLandmark ID="AAF4E336-75AE-4802-BF5B-5A054968DC84" X="92.083333" Y="34.074074" S="0.000000" />
            <TLFLandmark ID="DA50F8EA-E59A-480D-98F9-55710235D1B7" X="58.333333" Y="35.185185" S="0.000000" />
            <TLFLandmark ID="5F86768E-E0BA-45B2-BE5E-BB5A1F28C919" X="43.750000" Y="36.666667" S="0.000000" />
            <TLFLandmark ID="B3CF6567-2FEA-4169-B9EA-229652889D69" X="58.541667" Y="54.074074" S="0.000000" />
            <TLFLandmark ID="2C9C044F-73B6-4D31-B3B3-4645493B3745" X="69.791667" Y="59.259259" S="0.000000" />
            <TLFLandmark ID="CD5DE575-CD69-4349-89E4-2DCEFC47930E" X="74.375000" Y="56.296296" S="0.000000" />
            <TLFLandmark ID="7BFF3331-C358-461B-968E-F8ABB18A4C97" X="56.041667" Y="71.481481" S="1.000000" />
        </TLFLandmarkFile>
        <TLFLandmarkFile FileName="PHO00003.JPG">
            <TLFLandmark ID="65FE75D4-B829-4117-8076-0A6D116F6EE5" X="34.791667" Y="21.851852" S="1.000000" />
            <TLFLandmark ID="AAF4E336-75AE-4802-BF5B-5A054968DC84" X="89.166667" Y="25.185185" S="1.000000" />
            <TLFLandmark ID="DA50F8EA-E59A-480D-98F9-55710235D1B7" X="58.333333" Y="35.185185" S="0.000000" />
            <TLFLandmark ID="5F86768E-E0BA-45B2-BE5E-BB5A1F28C919" X="43.489583" Y="26.481481" S="1.000000" />
            <TLFLandmark ID="B3CF6567-2FEA-4169-B9EA-229652889D69" X="56.666667" Y="44.444444" S="1.000000" />
            <TLFLandmark ID="2C9C044F-73B6-4D31-B3B3-4645493B3745" X="69.791667" Y="59.259259" S="0.000000" />
            <TLFLandmark ID="CD5DE575-CD69-4349-89E4-2DCEFC47930E" X="74.375000" Y="56.296296" S="0.000000" />
            <TLFLandmark ID="7BFF3331-C358-461B-968E-F8ABB18A4C97" X="55.029762" Y="69.947090" S="1.000000" />
        </TLFLandmarkFile>
        <TLFLandmarkFile FileName="PHO00004.JPG">
            <TLFLandmark ID="65FE75D4-B829-4117-8076-0A6D116F6EE5" X="31.458333" Y="32.222222" S="0.000000" />
            <TLFLandmark ID="AAF4E336-75AE-4802-BF5B-5A054968DC84" X="85.937500" Y="25.370370" S="1.000000" />
            <TLFLandmark ID="DA50F8EA-E59A-480D-98F9-55710235D1B7" X="58.333333" Y="35.185185" S="0.000000" />
            <TLFLandmark ID="5F86768E-E0BA-45B2-BE5E-BB5A1F28C919" X="45.833333" Y="32.037037" S="1.000000" />
            <TLFLandmark ID="B3CF6567-2FEA-4169-B9EA-229652889D69" X="58.541667" Y="54.074074" S="0.000000" />
            <TLFLandmark ID="2C9C044F-73B6-4D31-B3B3-4645493B3745" X="69.791667" Y="59.259259" S="0.000000" />
            <TLFLandmark ID="CD5DE575-CD69-4349-89E4-2DCEFC47930E" X="74.375000" Y="56.296296" S="0.000000" />
            <TLFLandmark ID="7BFF3331-C358-461B-968E-F8ABB18A4C97" X="59.375000" Y="78.148148" S="0.000000" />
        </TLFLandmarkFile>
        <TLFLandmarkFile FileName="PHO00005.JPG">
            <TLFLandmark ID="65FE75D4-B829-4117-8076-0A6D116F6EE5" X="31.458333" Y="32.222222" S="0.000000" />
            <TLFLandmark ID="AAF4E336-75AE-4802-BF5B-5A054968DC84" X="92.083333" Y="34.074074" S="0.000000" />
            <TLFLandmark ID="DA50F8EA-E59A-480D-98F9-55710235D1B7" X="58.333333" Y="35.185185" S="0.000000" />
            <TLFLandmark ID="5F86768E-E0BA-45B2-BE5E-BB5A1F28C919" X="49.583333" Y="40.740741" S="1.000000" />
            <TLFLandmark ID="B3CF6567-2FEA-4169-B9EA-229652889D69" X="58.541667" Y="54.074074" S="0.000000" />
            <TLFLandmark ID="2C9C044F-73B6-4D31-B3B3-4645493B3745" X="69.791667" Y="59.259259" S="0.000000" />
            <TLFLandmark ID="CD5DE575-CD69-4349-89E4-2DCEFC47930E" X="74.375000" Y="56.296296" S="0.000000" />
            <TLFLandmark ID="7BFF3331-C358-461B-968E-F8ABB18A4C97" X="59.375000" Y="78.148148" S="0.000000" />
        </TLFLandmarkFile>
        <TLFLandmarkFile FileName="PHO00006.JPG">
            <TLFLandmark ID="65FE75D4-B829-4117-8076-0A6D116F6EE5" X="31.458333" Y="32.222222" S="0.000000" />
            <TLFLandmark ID="AAF4E336-75AE-4802-BF5B-5A054968DC84" X="90.000000" Y="18.518519" S="1.000000" />
            <TLFLandmark ID="DA50F8EA-E59A-480D-98F9-55710235D1B7" X="58.333333" Y="35.185185" S="0.000000" />
            <TLFLandmark ID="5F86768E-E0BA-45B2-BE5E-BB5A1F28C919" X="45.833333" Y="26.000000" S="1.000000" />
            <TLFLandmark ID="B3CF6567-2FEA-4169-B9EA-229652889D69" X="58.541667" Y="54.074074" S="0.000000" />
            <TLFLandmark ID="2C9C044F-73B6-4D31-B3B3-4645493B3745" X="69.791667" Y="59.259259" S="0.000000" />
            <TLFLandmark ID="CD5DE575-CD69-4349-89E4-2DCEFC47930E" X="74.375000" Y="56.296296" S="0.000000" />
            <TLFLandmark ID="7BFF3331-C358-461B-968E-F8ABB18A4C97" X="55.000000" Y="65.370370" S="1.000000" />
        </TLFLandmarkFile>
        <TLFLandmarkFile FileName="PHO00007.JPG">
            <TLFLandmark ID="65FE75D4-B829-4117-8076-0A6D116F6EE5" X="31.458333" Y="32.222222" S="0.000000" />
            <TLFLandmark ID="AAF4E336-75AE-4802-BF5B-5A054968DC84" X="88.125000" Y="40.740741" S="1.000000" />
            <TLFLandmark ID="DA50F8EA-E59A-480D-98F9-55710235D1B7" X="58.333333" Y="35.185185" S="0.000000" />
            <TLFLandmark ID="5F86768E-E0BA-45B2-BE5E-BB5A1F28C919" X="42.638889" Y="25.555556" S="1.000000" />
            <TLFLandmark ID="B3CF6567-2FEA-4169-B9EA-229652889D69" X="58.541667" Y="54.074074" S="0.000000" />
            <TLFLandmark ID="2C9C044F-73B6-4D31-B3B3-4645493B3745" X="69.791667" Y="59.259259" S="0.000000" />
            <TLFLandmark ID="CD5DE575-CD69-4349-89E4-2DCEFC47930E" X="74.375000" Y="56.296296" S="0.000000" />
            <TLFLandmark ID="7BFF3331-C358-461B-968E-F8ABB18A4C97" X="53.541667" Y="67.037037" S="1.000000" />
        </TLFLandmarkFile>
        <TLFLandmarkFile FileName="PHO00008.JPG">
            <TLFLandmark ID="65FE75D4-B829-4117-8076-0A6D116F6EE5" X="31.458333" Y="32.222222" S="0.000000" />
            <TLFLandmark ID="AAF4E336-75AE-4802-BF5B-5A054968DC84" X="90.000000" Y="26.666667" S="1.000000" />
            <TLFLandmark ID="DA50F8EA-E59A-480D-98F9-55710235D1B7" X="58.333333" Y="35.185185" S="0.000000" />
            <TLFLandmark ID="5F86768E-E0BA-45B2-BE5E-BB5A1F28C919" X="43.750000" Y="36.666667" S="0.000000" />
            <TLFLandmark ID="B3CF6567-2FEA-4169-B9EA-229652889D69" X="58.541667" Y="54.074074" S="0.000000" />
            <TLFLandmark ID="2C9C044F-73B6-4D31-B3B3-4645493B3745" X="69.791667" Y="59.259259" S="0.000000" />
            <TLFLandmark ID="CD5DE575-CD69-4349-89E4-2DCEFC47930E" X="74.375000" Y="56.296296" S="0.000000" />
            <TLFLandmark ID="7BFF3331-C358-461B-968E-F8ABB18A4C97" X="59.375000" Y="78.148148" S="0.000000" />
        </TLFLandmarkFile>
        <TLFLandmarkFile FileName="PHO00009.JPG">
            <TLFLandmark ID="65FE75D4-B829-4117-8076-0A6D116F6EE5" X="31.458333" Y="32.222222" S="0.000000" />
            <TLFLandmark ID="AAF4E336-75AE-4802-BF5B-5A054968DC84" X="87.708333" Y="32.962963" S="1.000000" />
            <TLFLandmark ID="DA50F8EA-E59A-480D-98F9-55710235D1B7" X="58.333333" Y="35.185185" S="0.000000" />
            <TLFLandmark ID="5F86768E-E0BA-45B2-BE5E-BB5A1F28C919" X="35.520833" Y="23.148148" S="1.000000" />
            <TLFLandmark ID="B3CF6567-2FEA-4169-B9EA-229652889D69" X="58.541667" Y="54.074074" S="0.000000" />
            <TLFLandmark ID="2C9C044F-73B6-4D31-B3B3-4645493B3745" X="69.791667" Y="59.259259" S="0.000000" />
            <TLFLandmark ID="CD5DE575-CD69-4349-89E4-2DCEFC47930E" X="74.375000" Y="56.296296" S="0.000000" />
            <TLFLandmark ID="7BFF3331-C358-461B-968E-F8ABB18A4C97" X="59.375000" Y="78.148148" S="0.000000" />
        </TLFLandmarkFile>
        <TLFLandmarkFile FileName="PHO00010.JPG">
            <TLFLandmark ID="65FE75D4-B829-4117-8076-0A6D116F6EE5" X="31.458333" Y="32.222222" S="0.000000" />
            <TLFLandmark ID="AAF4E336-75AE-4802-BF5B-5A054968DC84" X="92.083333" Y="34.074074" S="0.000000" />
            <TLFLandmark ID="DA50F8EA-E59A-480D-98F9-55710235D1B7" X="58.333333" Y="35.185185" S="0.000000" />
            <TLFLandmark ID="5F86768E-E0BA-45B2-BE5E-BB5A1F28C919" X="43.750000" Y="36.666667" S="0.000000" />
            <TLFLandmark ID="B3CF6567-2FEA-4169-B9EA-229652889D69" X="58.541667" Y="54.074074" S="0.000000" />
            <TLFLandmark ID="2C9C044F-73B6-4D31-B3B3-4645493B3745" X="69.791667" Y="59.259259" S="0.000000" />
            <TLFLandmark ID="CD5DE575-CD69-4349-89E4-2DCEFC47930E" X="74.375000" Y="56.296296" S="0.000000" />
            <TLFLandmark ID="7BFF3331-C358-461B-968E-F8ABB18A4C97" X="59.375000" Y="78.148148" S="0.000000" />
        </TLFLandmarkFile>
        <TLFLandmarkFile FileName="PHO00011.JPG">
            <TLFLandmark ID="65FE75D4-B829-4117-8076-0A6D116F6EE5" X="31.458333" Y="32.222222" S="0.000000" />
            <TLFLandmark ID="AAF4E336-75AE-4802-BF5B-5A054968DC84" X="90.922619" Y="26.190476" S="1.000000" />
            <TLFLandmark ID="DA50F8EA-E59A-480D-98F9-55710235D1B7" X="58.333333" Y="35.185185" S="0.000000" />
            <TLFLandmark ID="5F86768E-E0BA-45B2-BE5E-BB5A1F28C919" X="47.962963" Y="26.584362" S="1.000000" />
            <TLFLandmark ID="B3CF6567-2FEA-4169-B9EA-229652889D69" X="58.541667" Y="54.074074" S="0.000000" />
            <TLFLandmark ID="2C9C044F-73B6-4D31-B3B3-4645493B3745" X="65.000000" Y="53.333333" S="1.000000" />
            <TLFLandmark ID="CD5DE575-CD69-4349-89E4-2DCEFC47930E" X="74.375000" Y="56.296296" S="0.000000" />
            <TLFLandmark ID="7BFF3331-C358-461B-968E-F8ABB18A4C97" X="59.375000" Y="78.148148" S="0.000000" />
        </TLFLandmarkFile>
        <TLFLandmarkFile FileName="PHO00012.JPG">
            <TLFLandmark ID="65FE75D4-B829-4117-8076-0A6D116F6EE5" X="31.458333" Y="32.222222" S="0.000000" />
            <TLFLandmark ID="AAF4E336-75AE-4802-BF5B-5A054968DC84" X="86.875000" Y="26.296296" S="1.000000" />
            <TLFLandmark ID="DA50F8EA-E59A-480D-98F9-55710235D1B7" X="58.333333" Y="35.185185" S="0.000000" />
            <TLFLandmark ID="5F86768E-E0BA-45B2-BE5E-BB5A1F28C919" X="54.166667" Y="25.185185" S="1.000000" />
            <TLFLandmark ID="B3CF6567-2FEA-4169-B9EA-229652889D69" X="58.541667" Y="54.074074" S="0.000000" />
            <TLFLandmark ID="2C9C044F-73B6-4D31-B3B3-4645493B3745" X="69.791667" Y="59.259259" S="0.000000" />
            <TLFLandmark ID="CD5DE575-CD69-4349-89E4-2DCEFC47930E" X="74.375000" Y="56.296296" S="0.000000" />
            <TLFLandmark ID="7BFF3331-C358-461B-968E-F8ABB18A4C97" X="59.375000" Y="78.148148" S="0.000000" />
        </TLFLandmarkFile>
        <TLFLandmarkFile FileName="PHO00013.JPG">
            <TLFLandmark ID="65FE75D4-B829-4117-8076-0A6D116F6EE5" X="31.458333" Y="32.222222" S="0.000000" />
            <TLFLandmark ID="AAF4E336-75AE-4802-BF5B-5A054968DC84" X="89.427083" Y="37.129630" S="1.000000" />
            <TLFLandmark ID="DA50F8EA-E59A-480D-98F9-55710235D1B7" X="58.333333" Y="35.185185" S="0.000000" />
            <TLFLandmark ID="5F86768E-E0BA-45B2-BE5E-BB5A1F28C919" X="43.750000" Y="36.666667" S="0.000000" />
            <TLFLandmark ID="B3CF6567-2FEA-4169-B9EA-229652889D69" X="54.166667" Y="45.925926" S="1.000000" />
            <TLFLandmark ID="2C9C044F-73B6-4D31-B3B3-4645493B3745" X="69.791667" Y="59.259259" S="0.000000" />
            <TLFLandmark ID="CD5DE575-CD69-4349-89E4-2DCEFC47930E" X="74.375000" Y="56.296296" S="0.000000" />
            <TLFLandmark ID="7BFF3331-C358-461B-968E-F8ABB18A4C97" X="53.333333" Y="74.074074" S="1.000000" />
        </TLFLandmarkFile>
        <TLFLandmarkFile FileName="PHO00014.JPG">
            <TLFLandmark ID="65FE75D4-B829-4117-8076-0A6D116F6EE5" X="31.458333" Y="32.222222" S="0.000000" />
            <TLFLandmark ID="AAF4E336-75AE-4802-BF5B-5A054968DC84" X="89.010417" Y="25.648148" S="1.000000" />
            <TLFLandmark ID="DA50F8EA-E59A-480D-98F9-55710235D1B7" X="58.333333" Y="35.185185" S="0.000000" />
            <TLFLandmark ID="5F86768E-E0BA-45B2-BE5E-BB5A1F28C919" X="43.333333" Y="31.111111" S="1.000000" />
            <TLFLandmark ID="B3CF6567-2FEA-4169-B9EA-229652889D69" X="55.208333" Y="44.814815" S="1.000000" />
            <TLFLandmark ID="2C9C044F-73B6-4D31-B3B3-4645493B3745" X="69.791667" Y="59.259259" S="0.000000" />
            <TLFLandmark ID="CD5DE575-CD69-4349-89E4-2DCEFC47930E" X="74.375000" Y="56.296296" S="0.000000" />
            <TLFLandmark ID="7BFF3331-C358-461B-968E-F8ABB18A4C97" X="54.895833" Y="70.925926" S="1.000000" />
        </TLFLandmarkFile>
        <TLFLandmarkFile FileName="PHO00015.JPG">
            <TLFLandmark ID="65FE75D4-B829-4117-8076-0A6D116F6EE5" X="31.458333" Y="32.222222" S="0.000000" />
            <TLFLandmark ID="AAF4E336-75AE-4802-BF5B-5A054968DC84" X="94.583333" Y="24.444444" S="1.000000" />
            <TLFLandmark ID="DA50F8EA-E59A-480D-98F9-55710235D1B7" X="58.333333" Y="35.185185" S="0.000000" />
            <TLFLandmark ID="5F86768E-E0BA-45B2-BE5E-BB5A1F28C919" X="43.750000" Y="36.666667" S="0.000000" />
            <TLFLandmark ID="B3CF6567-2FEA-4169-B9EA-229652889D69" X="58.541667" Y="54.074074" S="0.000000" />
            <TLFLandmark ID="2C9C044F-73B6-4D31-B3B3-4645493B3745" X="69.791667" Y="59.259259" S="0.000000" />
            <TLFLandmark ID="CD5DE575-CD69-4349-89E4-2DCEFC47930E" X="74.375000" Y="56.296296" S="0.000000" />
            <TLFLandmark ID="7BFF3331-C358-461B-968E-F8ABB18A4C97" X="58.750000" Y="67.407407" S="1.000000" />
        </TLFLandmarkFile>
        <TLFLandmarkFile FileName="PHO00016.JPG">
            <TLFLandmark ID="65FE75D4-B829-4117-8076-0A6D116F6EE5" X="31.458333" Y="32.222222" S="0.000000" />
            <TLFLandmark ID="AAF4E336-75AE-4802-BF5B-5A054968DC84" X="88.489583" Y="24.351852" S="1.000000" />
            <TLFLandmark ID="DA50F8EA-E59A-480D-98F9-55710235D1B7" X="58.333333" Y="35.185185" S="0.000000" />
            <TLFLandmark ID="5F86768E-E0BA-45B2-BE5E-BB5A1F28C919" X="42.041667" Y="30.740741" S="1.000000" />
            <TLFLandmark ID="B3CF6567-2FEA-4169-B9EA-229652889D69" X="55.833333" Y="45.925926" S="1.000000" />
            <TLFLandmark ID="2C9C044F-73B6-4D31-B3B3-4645493B3745" X="69.791667" Y="59.259259" S="0.000000" />
            <TLFLandmark ID="CD5DE575-CD69-4349-89E4-2DCEFC47930E" X="74.375000" Y="56.296296" S="0.000000" />
            <TLFLandmark ID="7BFF3331-C358-461B-968E-F8ABB18A4C97" X="54.208333" Y="72.370370" S="1.000000" />
        </TLFLandmarkFile>
        <TLFLandmarkFile FileName="PHO00017.JPG">
            <TLFLandmark ID="65FE75D4-B829-4117-8076-0A6D116F6EE5" X="30.833333" Y="20.740741" S="1.000000" />
            <TLFLandmark ID="AAF4E336-75AE-4802-BF5B-5A054968DC84" X="88.125000" Y="26.049383" S="1.000000" />
            <TLFLandmark ID="DA50F8EA-E59A-480D-98F9-55710235D1B7" X="58.333333" Y="35.185185" S="0.000000" />
            <TLFLandmark ID="5F86768E-E0BA-45B2-BE5E-BB5A1F28C919" X="46.458333" Y="27.555556" S="1.000000" />
            <TLFLandmark ID="B3CF6567-2FEA-4169-B9EA-229652889D69" X="58.541667" Y="54.074074" S="0.000000" />
            <TLFLandmark ID="2C9C044F-73B6-4D31-B3B3-4645493B3745" X="69.791667" Y="59.259259" S="0.000000" />
            <TLFLandmark ID="CD5DE575-CD69-4349-89E4-2DCEFC47930E" X="74.375000" Y="56.296296" S="0.000000" />
            <TLFLandmark ID="7BFF3331-C358-461B-968E-F8ABB18A4C97" X="55.338542" Y="68.425926" S="1.000000" />
        </TLFLandmarkFile>
        <TLFLandmarkFile FileName="PHO00018.JPG">
            <TLFLandmark ID="65FE75D4-B829-4117-8076-0A6D116F6EE5" X="31.875000" Y="18.148148" S="1.000000" />
            <TLFLandmark ID="AAF4E336-75AE-4802-BF5B-5A054968DC84" X="86.319444" Y="20.123457" S="1.000000" />
            <TLFLandmark ID="DA50F8EA-E59A-480D-98F9-55710235D1B7" X="58.333333" Y="35.185185" S="0.000000" />
            <TLFLandmark ID="5F86768E-E0BA-45B2-BE5E-BB5A1F28C919" X="45.763889" Y="26.296296" S="1.000000" />
            <TLFLandmark ID="B3CF6567-2FEA-4169-B9EA-229652889D69" X="58.541667" Y="54.074074" S="0.000000" />
            <TLFLandmark ID="2C9C044F-73B6-4D31-B3B3-4645493B3745" X="69.791667" Y="59.259259" S="0.000000" />
            <TLFLandmark ID="CD5DE575-CD69-4349-89E4-2DCEFC47930E" X="74.375000" Y="56.296296" S="0.000000" />
            <TLFLandmark ID="7BFF3331-C358-461B-968E-F8ABB18A4C97" X="59.375000" Y="78.148148" S="0.000000" />
        </TLFLandmarkFile>
        <TLFLandmarkFile FileName="PHO00019.JPG">
            <TLFLandmark ID="65FE75D4-B829-4117-8076-0A6D116F6EE5" X="31.458333" Y="32.222222" S="0.000000" />
            <TLFLandmark ID="AAF4E336-75AE-4802-BF5B-5A054968DC84" X="92.083333" Y="34.074074" S="0.000000" />
            <TLFLandmark ID="DA50F8EA-E59A-480D-98F9-55710235D1B7" X="58.333333" Y="35.185185" S="0.000000" />
            <TLFLandmark ID="5F86768E-E0BA-45B2-BE5E-BB5A1F28C919" X="40.535714" Y="33.544974" S="1.000000" />
            <TLFLandmark ID="B3CF6567-2FEA-4169-B9EA-229652889D69" X="58.541667" Y="54.074074" S="0.000000" />
            <TLFLandmark ID="2C9C044F-73B6-4D31-B3B3-4645493B3745" X="69.791667" Y="59.259259" S="0.000000" />
            <TLFLandmark ID="CD5DE575-CD69-4349-89E4-2DCEFC47930E" X="74.375000" Y="56.296296" S="0.000000" />
            <TLFLandmark ID="7BFF3331-C358-461B-968E-F8ABB18A4C97" X="59.375000" Y="78.148148" S="0.000000" />
        </TLFLandmarkFile>
    </TLFLandmarkFiles>
</TLFDBLandmarks>
