<?xml version="1.0" ?>
<TLFDBLandmarks>
    <TLFLandmarkAttributes>
        <TLFLandmarkAttr ID="65FE75D4-B829-4117-8076-0A6D116F6EE5" ClassName="wing-1" Color="33023" />
        <TLFLandmarkAttr ID="AAF4E336-75AE-4802-BF5B-5A054968DC84" ClassName="wing-2" Color="16777215" />
        <TLFLandmarkAttr ID="DA50F8EA-E59A-480D-98F9-55710235D1B7" ClassName="wing-3" Color="65535" />
        <TLFLandmarkAttr ID="5F86768E-E0BA-45B2-BE5E-BB5A1F28C919" ClassName="wing-4" Color="16711935" />
        <TLFLandmarkAttr ID="B3CF6567-2FEA-4169-B9EA-229652889D69" ClassName="wing-5" Color="16776960" />
        <TLFLandmarkAttr ID="2C9C044F-73B6-4D31-B3B3-4645493B3745" ClassName="wing-6" Color="16711680" />
        <TLFLandmarkAttr ID="CD5DE575-CD69-4349-89E4-2DCEFC47930E" ClassName="wing-7" Color="65280" />
        <TLFLandmarkAttr ID="7BFF3331-C358-461B-968E-F8ABB18A4C97" ClassName="wing-8" Color="255" />
    </TLFLandmarkAttributes>
    <TLFLandmarkFiles>
        <TLFLandmarkFile FileName="PHO00016.JPG">
            <TLFLandmark ID="65FE75D4-B829-4117-8076-0A6D116F6EE5" X="22.291667" Y="29.259259" S="0.000000" />
            <TLFLandmark ID="AAF4E336-75AE-4802-BF5B-5A054968DC84" X="89.791667" Y="21.481481" S="0.000000" />
            <TLFLandmark ID="DA50F8EA-E59A-480D-98F9-55710235D1B7" X="52.708333" Y="35.185185" S="0.000000" />
            <TLFLandmark ID="5F86768E-E0BA-45B2-BE5E-BB5A1F28C919" X="29.861111" Y="35.555556" S="1.000000" />
            <TLFLandmark ID="B3CF6567-2FEA-4169-B9EA-229652889D69" X="52.083333" Y="54.074074" S="1.000000" />
            <TLFLandmark ID="2C9C044F-73B6-4D31-B3B3-4645493B3745" X="62.916667" Y="60.000000" S="1.000000" />
            <TLFLandmark ID="CD5DE575-CD69-4349-89E4-2DCEFC47930E" X="70.297619" Y="57.883598" S="1.000000" />
            <TLFLandmark ID="7BFF3331-C358-461B-968E-F8ABB18A4C97" X="52.604167" Y="92.777778" S="1.000000" />
        </TLFLandmarkFile>
        <TLFLandmarkFile FileName="PHO00017.JPG">
            <TLFLandmark ID="65FE75D4-B829-4117-8076-0A6D116F6EE5" X="18.645833" Y="24.259259" S="1.000000" />
            <TLFLandmark ID="AAF4E336-75AE-4802-BF5B-5A054968DC84" X="89.791667" Y="21.481481" S="0.000000" />
            <TLFLandmark ID="DA50F8EA-E59A-480D-98F9-55710235D1B7" X="52.708333" Y="35.185185" S="0.000000" />
            <TLFLandmark ID="5F86768E-E0BA-45B2-BE5E-BB5A1F28C919" X="34.236111" Y="31.728395" S="1.000000" />
            <TLFLandmark ID="B3CF6567-2FEA-4169-B9EA-229652889D69" X="52.291667" Y="54.814815" S="0.000000" />
            <TLFLandmark ID="2C9C044F-73B6-4D31-B3B3-4645493B3745" X="63.402778" Y="57.901235" S="1.000000" />
            <TLFLandmark ID="CD5DE575-CD69-4349-89E4-2DCEFC47930E" X="71.041667" Y="55.185185" S="1.000000" />
            <TLFLandmark ID="7BFF3331-C358-461B-968E-F8ABB18A4C97" X="53.125000" Y="88.518519" S="1.000000" />
        </TLFLandmarkFile>
        <TLFLandmarkFile FileName="PHO00018.JPG">
            <TLFLandmark ID="65FE75D4-B829-4117-8076-0A6D116F6EE5" X="22.291667" Y="29.259259" S="0.000000" />
            <TLFLandmark ID="AAF4E336-75AE-4802-BF5B-5A054968DC84" X="89.791667" Y="21.481481" S="0.000000" />
            <TLFLandmark ID="DA50F8EA-E59A-480D-98F9-55710235D1B7" X="52.708333" Y="35.185185" S="0.000000" />
            <TLFLandmark ID="5F86768E-E0BA-45B2-BE5E-BB5A1F28C919" X="34.583333" Y="35.555556" S="1.000000" />
            <TLFLandmark ID="B3CF6567-2FEA-4169-B9EA-229652889D69" X="54.500000" Y="54.370370" S="1.000000" />
            <TLFLandmark ID="2C9C044F-73B6-4D31-B3B3-4645493B3745" X="64.895833" Y="61.296296" S="1.000000" />
            <TLFLandmark ID="CD5DE575-CD69-4349-89E4-2DCEFC47930E" X="72.261905" Y="57.989418" S="1.000000" />
            <TLFLandmark ID="7BFF3331-C358-461B-968E-F8ABB18A4C97" X="51.250000" Y="81.111111" S="0.000000" />
        </TLFLandmarkFile>
        <TLFLandmarkFile FileName="PHO00019.JPG">
            <TLFLandmark ID="65FE75D4-B829-4117-8076-0A6D116F6EE5" X="22.291667" Y="29.259259" S="0.000000" />
            <TLFLandmark ID="AAF4E336-75AE-4802-BF5B-5A054968DC84" X="89.791667" Y="21.481481" S="0.000000" />
            <TLFLandmark ID="DA50F8EA-E59A-480D-98F9-55710235D1B7" X="52.708333" Y="35.185185" S="0.000000" />
            <TLFLandmark ID="5F86768E-E0BA-45B2-BE5E-BB5A1F28C919" X="29.270833" Y="32.777778" S="1.000000" />
            <TLFLandmark ID="B3CF6567-2FEA-4169-B9EA-229652889D69" X="52.797619" Y="53.333333" S="1.000000" />
            <TLFLandmark ID="2C9C044F-73B6-4D31-B3B3-4645493B3745" X="63.333333" Y="64.814815" S="0.000000" />
            <TLFLandmark ID="CD5DE575-CD69-4349-89E4-2DCEFC47930E" X="69.166667" Y="57.777778" S="1.000000" />
            <TLFLandmark ID="7BFF3331-C358-461B-968E-F8ABB18A4C97" X="50.729167" Y="88.703704" S="1.000000" />
        </TLFLandmarkFile>
        <TLFLandmarkFile FileName="PHO00020.JPG">
            <TLFLandmark ID="65FE75D4-B829-4117-8076-0A6D116F6EE5" X="16.666667" Y="26.666667" S="1.000000" />
            <TLFLandmark ID="AAF4E336-75AE-4802-BF5B-5A054968DC84" X="89.791667" Y="21.481481" S="0.000000" />
            <TLFLandmark ID="DA50F8EA-E59A-480D-98F9-55710235D1B7" X="52.708333" Y="35.185185" S="0.000000" />
            <TLFLandmark ID="5F86768E-E0BA-45B2-BE5E-BB5A1F28C919" X="31.166667" Y="33.481481" S="1.000000" />
            <TLFLandmark ID="B3CF6567-2FEA-4169-B9EA-229652889D69" X="52.291667" Y="54.814815" S="0.000000" />
            <TLFLandmark ID="2C9C044F-73B6-4D31-B3B3-4645493B3745" X="63.333333" Y="64.814815" S="0.000000" />
            <TLFLandmark ID="CD5DE575-CD69-4349-89E4-2DCEFC47930E" X="71.041667" Y="57.654321" S="1.000000" />
            <TLFLandmark ID="7BFF3331-C358-461B-968E-F8ABB18A4C97" X="51.250000" Y="81.111111" S="0.000000" />
        </TLFLandmarkFile>
        <TLFLandmarkFile FileName="PHO00021.JPG">
            <TLFLandmark ID="65FE75D4-B829-4117-8076-0A6D116F6EE5" X="17.916667" Y="25.925926" S="1.000000" />
            <TLFLandmark ID="AAF4E336-75AE-4802-BF5B-5A054968DC84" X="89.791667" Y="21.481481" S="0.000000" />
            <TLFLandmark ID="DA50F8EA-E59A-480D-98F9-55710235D1B7" X="52.708333" Y="35.185185" S="0.000000" />
            <TLFLandmark ID="5F86768E-E0BA-45B2-BE5E-BB5A1F28C919" X="31.527778" Y="32.839506" S="1.000000" />
            <TLFLandmark ID="B3CF6567-2FEA-4169-B9EA-229652889D69" X="53.229167" Y="52.777778" S="1.000000" />
            <TLFLandmark ID="2C9C044F-73B6-4D31-B3B3-4645493B3745" X="63.645833" Y="61.111111" S="1.000000" />
            <TLFLandmark ID="CD5DE575-CD69-4349-89E4-2DCEFC47930E" X="71.354167" Y="57.222222" S="1.000000" />
            <TLFLandmark ID="7BFF3331-C358-461B-968E-F8ABB18A4C97" X="53.541667" Y="89.259259" S="1.000000" />
        </TLFLandmarkFile>
        <TLFLandmarkFile FileName="PHO00022.JPG">
            <TLFLandmark ID="65FE75D4-B829-4117-8076-0A6D116F6EE5" X="16.041667" Y="25.555556" S="1.000000" />
            <TLFLandmark ID="AAF4E336-75AE-4802-BF5B-5A054968DC84" X="95.000000" Y="14.814815" S="1.000000" />
            <TLFLandmark ID="DA50F8EA-E59A-480D-98F9-55710235D1B7" X="52.708333" Y="35.185185" S="0.000000" />
            <TLFLandmark ID="5F86768E-E0BA-45B2-BE5E-BB5A1F28C919" X="30.937500" Y="33.271605" S="1.000000" />
            <TLFLandmark ID="B3CF6567-2FEA-4169-B9EA-229652889D69" X="52.291667" Y="54.814815" S="0.000000" />
            <TLFLandmark ID="2C9C044F-73B6-4D31-B3B3-4645493B3745" X="63.333333" Y="64.814815" S="0.000000" />
            <TLFLandmark ID="CD5DE575-CD69-4349-89E4-2DCEFC47930E" X="69.125000" Y="57.407407" S="1.000000" />
            <TLFLandmark ID="7BFF3331-C358-461B-968E-F8ABB18A4C97" X="50.000000" Y="91.851852" S="1.000000" />
        </TLFLandmarkFile>
        <TLFLandmarkFile FileName="PHO00023.JPG">
            <TLFLandmark ID="65FE75D4-B829-4117-8076-0A6D116F6EE5" X="16.666667" Y="25.185185" S="1.000000" />
            <TLFLandmark ID="AAF4E336-75AE-4802-BF5B-5A054968DC84" X="89.791667" Y="21.481481" S="0.000000" />
            <TLFLandmark ID="DA50F8EA-E59A-480D-98F9-55710235D1B7" X="52.708333" Y="35.185185" S="0.000000" />
            <TLFLandmark ID="5F86768E-E0BA-45B2-BE5E-BB5A1F28C919" X="30.041667" Y="32.370370" S="1.000000" />
            <TLFLandmark ID="B3CF6567-2FEA-4169-B9EA-229652889D69" X="52.430556" Y="52.716049" S="1.000000" />
            <TLFLandmark ID="2C9C044F-73B6-4D31-B3B3-4645493B3745" X="62.083333" Y="60.740741" S="1.000000" />
            <TLFLandmark ID="CD5DE575-CD69-4349-89E4-2DCEFC47930E" X="70.416667" Y="57.925926" S="1.000000" />
            <TLFLandmark ID="7BFF3331-C358-461B-968E-F8ABB18A4C97" X="51.354167" Y="92.037037" S="1.000000" />
        </TLFLandmarkFile>
        <TLFLandmarkFile FileName="PHO00024.JPG">
            <TLFLandmark ID="65FE75D4-B829-4117-8076-0A6D116F6EE5" X="17.083333" Y="27.037037" S="1.000000" />
            <TLFLandmark ID="AAF4E336-75AE-4802-BF5B-5A054968DC84" X="94.583333" Y="13.580247" S="1.000000" />
            <TLFLandmark ID="DA50F8EA-E59A-480D-98F9-55710235D1B7" X="52.708333" Y="35.185185" S="0.000000" />
            <TLFLandmark ID="5F86768E-E0BA-45B2-BE5E-BB5A1F28C919" X="30.125000" Y="34.296296" S="1.000000" />
            <TLFLandmark ID="B3CF6567-2FEA-4169-B9EA-229652889D69" X="51.736111" Y="53.950617" S="1.000000" />
            <TLFLandmark ID="2C9C044F-73B6-4D31-B3B3-4645493B3745" X="61.458333" Y="61.851852" S="1.000000" />
            <TLFLandmark ID="CD5DE575-CD69-4349-89E4-2DCEFC47930E" X="69.791667" Y="58.518519" S="1.000000" />
            <TLFLandmark ID="7BFF3331-C358-461B-968E-F8ABB18A4C97" X="51.250000" Y="81.111111" S="0.000000" />
        </TLFLandmarkFile>
        <TLFLandmarkFile FileName="PHO00025.JPG">
            <TLFLandmark ID="65FE75D4-B829-4117-8076-0A6D116F6EE5" X="22.291667" Y="29.259259" S="0.000000" />
            <TLFLandmark ID="AAF4E336-75AE-4802-BF5B-5A054968DC84" X="89.791667" Y="21.481481" S="0.000000" />
            <TLFLandmark ID="DA50F8EA-E59A-480D-98F9-55710235D1B7" X="52.708333" Y="35.185185" S="0.000000" />
            <TLFLandmark ID="5F86768E-E0BA-45B2-BE5E-BB5A1F28C919" X="32.447917" Y="31.203704" S="1.000000" />
            <TLFLandmark ID="B3CF6567-2FEA-4169-B9EA-229652889D69" X="55.684524" Y="53.280423" S="1.000000" />
            <TLFLandmark ID="2C9C044F-73B6-4D31-B3B3-4645493B3745" X="63.541667" Y="58.148148" S="1.000000" />
            <TLFLandmark ID="CD5DE575-CD69-4349-89E4-2DCEFC47930E" X="72.500000" Y="56.296296" S="1.000000" />
            <TLFLandmark ID="7BFF3331-C358-461B-968E-F8ABB18A4C97" X="51.250000" Y="81.111111" S="0.000000" />
        </TLFLandmarkFile>
        <TLFLandmarkFile FileName="PHO00026.JPG">
            <TLFLandmark ID="65FE75D4-B829-4117-8076-0A6D116F6EE5" X="22.291667" Y="29.259259" S="0.000000" />
            <TLFLandmark ID="AAF4E336-75AE-4802-BF5B-5A054968DC84" X="89.791667" Y="21.481481" S="0.000000" />
            <TLFLandmark ID="DA50F8EA-E59A-480D-98F9-55710235D1B7" X="52.708333" Y="35.185185" S="0.000000" />
            <TLFLandmark ID="5F86768E-E0BA-45B2-BE5E-BB5A1F28C919" X="31.666667" Y="32.592593" S="1.000000" />
            <TLFLandmark ID="B3CF6567-2FEA-4169-B9EA-229652889D69" X="52.604167" Y="52.777778" S="1.000000" />
            <TLFLandmark ID="2C9C044F-73B6-4D31-B3B3-4645493B3745" X="60.486111" Y="58.888889" S="1.000000" />
            <TLFLandmark ID="CD5DE575-CD69-4349-89E4-2DCEFC47930E" X="69.895833" Y="56.481481" S="1.000000" />
            <TLFLandmark ID="7BFF3331-C358-461B-968E-F8ABB18A4C97" X="52.847222" Y="89.012346" S="1.000000" />
        </TLFLandmarkFile>
        <TLFLandmarkFile FileName="PHO00027.JPG">
            <TLFLandmark ID="65FE75D4-B829-4117-8076-0A6D116F6EE5" X="22.291667" Y="29.259259" S="0.000000" />
            <TLFLandmark ID="AAF4E336-75AE-4802-BF5B-5A054968DC84" X="89.791667" Y="21.481481" S="0.000000" />
            <TLFLandmark ID="DA50F8EA-E59A-480D-98F9-55710235D1B7" X="52.708333" Y="35.185185" S="0.000000" />
            <TLFLandmark ID="5F86768E-E0BA-45B2-BE5E-BB5A1F28C919" X="34.479167" Y="35.555556" S="1.000000" />
            <TLFLandmark ID="B3CF6567-2FEA-4169-B9EA-229652889D69" X="53.541667" Y="52.222222" S="1.000000" />
            <TLFLandmark ID="2C9C044F-73B6-4D31-B3B3-4645493B3745" X="64.479167" Y="59.814815" S="1.000000" />
            <TLFLandmark ID="CD5DE575-CD69-4349-89E4-2DCEFC47930E" X="72.916667" Y="57.037037" S="1.000000" />
            <TLFLandmark ID="7BFF3331-C358-461B-968E-F8ABB18A4C97" X="54.444444" Y="91.851852" S="1.000000" />
        </TLFLandmarkFile>
        <TLFLandmarkFile FileName="PHO00028.JPG">
            <TLFLandmark ID="65FE75D4-B829-4117-8076-0A6D116F6EE5" X="15.416667" Y="27.407407" S="1.000000" />
            <TLFLandmark ID="AAF4E336-75AE-4802-BF5B-5A054968DC84" X="89.791667" Y="21.481481" S="0.000000" />
            <TLFLandmark ID="DA50F8EA-E59A-480D-98F9-55710235D1B7" X="52.708333" Y="35.185185" S="0.000000" />
            <TLFLandmark ID="5F86768E-E0BA-45B2-BE5E-BB5A1F28C919" X="28.020833" Y="34.012346" S="1.000000" />
            <TLFLandmark ID="B3CF6567-2FEA-4169-B9EA-229652889D69" X="50.791667" Y="54.148148" S="1.000000" />
            <TLFLandmark ID="2C9C044F-73B6-4D31-B3B3-4645493B3745" X="62.083333" Y="61.481481" S="1.000000" />
            <TLFLandmark ID="CD5DE575-CD69-4349-89E4-2DCEFC47930E" X="69.196429" Y="58.042328" S="1.000000" />
            <TLFLandmark ID="7BFF3331-C358-461B-968E-F8ABB18A4C97" X="49.791667" Y="92.222222" S="1.000000" />
        </TLFLandmarkFile>
        <TLFLandmarkFile FileName="PHO00029.JPG">
            <TLFLandmark ID="65FE75D4-B829-4117-8076-0A6D116F6EE5" X="22.291667" Y="29.259259" S="0.000000" />
            <TLFLandmark ID="AAF4E336-75AE-4802-BF5B-5A054968DC84" X="89.791667" Y="21.481481" S="0.000000" />
            <TLFLandmark ID="DA50F8EA-E59A-480D-98F9-55710235D1B7" X="52.708333" Y="35.185185" S="0.000000" />
            <TLFLandmark ID="5F86768E-E0BA-45B2-BE5E-BB5A1F28C919" X="32.708333" Y="32.469136" S="1.000000" />
            <TLFLandmark ID="B3CF6567-2FEA-4169-B9EA-229652889D69" X="52.291667" Y="54.814815" S="0.000000" />
            <TLFLandmark ID="2C9C044F-73B6-4D31-B3B3-4645493B3745" X="63.333333" Y="64.814815" S="0.000000" />
            <TLFLandmark ID="CD5DE575-CD69-4349-89E4-2DCEFC47930E" X="71.041667" Y="56.666667" S="1.000000" />
            <TLFLandmark ID="7BFF3331-C358-461B-968E-F8ABB18A4C97" X="52.500000" Y="90.370370" S="1.000000" />
        </TLFLandmarkFile>
        <TLFLandmarkFile FileName="PHO00030.JPG">
            <TLFLandmark ID="65FE75D4-B829-4117-8076-0A6D116F6EE5" X="17.916667" Y="17.037037" S="1.000000" />
            <TLFLandmark ID="AAF4E336-75AE-4802-BF5B-5A054968DC84" X="89.791667" Y="21.481481" S="0.000000" />
            <TLFLandmark ID="DA50F8EA-E59A-480D-98F9-55710235D1B7" X="52.708333" Y="35.185185" S="0.000000" />
            <TLFLandmark ID="5F86768E-E0BA-45B2-BE5E-BB5A1F28C919" X="32.083333" Y="25.333333" S="1.000000" />
            <TLFLandmark ID="B3CF6567-2FEA-4169-B9EA-229652889D69" X="52.291667" Y="54.814815" S="0.000000" />
            <TLFLandmark ID="2C9C044F-73B6-4D31-B3B3-4645493B3745" X="62.083333" Y="55.555556" S="1.000000" />
            <TLFLandmark ID="CD5DE575-CD69-4349-89E4-2DCEFC47930E" X="70.138889" Y="53.086420" S="1.000000" />
            <TLFLandmark ID="7BFF3331-C358-461B-968E-F8ABB18A4C97" X="51.666667" Y="84.444444" S="1.000000" />
        </TLFLandmarkFile>
        <TLFLandmarkFile FileName="PHO00031.JPG">
            <TLFLandmark ID="65FE75D4-B829-4117-8076-0A6D116F6EE5" X="17.638889" Y="27.283951" S="1.000000" />
            <TLFLandmark ID="AAF4E336-75AE-4802-BF5B-5A054968DC84" X="89.791667" Y="21.481481" S="0.000000" />
            <TLFLandmark ID="DA50F8EA-E59A-480D-98F9-55710235D1B7" X="52.708333" Y="35.185185" S="0.000000" />
            <TLFLandmark ID="5F86768E-E0BA-45B2-BE5E-BB5A1F28C919" X="33.958333" Y="33.703704" S="1.000000" />
            <TLFLandmark ID="B3CF6567-2FEA-4169-B9EA-229652889D69" X="52.500000" Y="54.074074" S="1.000000" />
            <TLFLandmark ID="2C9C044F-73B6-4D31-B3B3-4645493B3745" X="62.291667" Y="62.222222" S="1.000000" />
            <TLFLandmark ID="CD5DE575-CD69-4349-89E4-2DCEFC47930E" X="71.583333" Y="57.185185" S="1.000000" />
            <TLFLandmark ID="7BFF3331-C358-461B-968E-F8ABB18A4C97" X="54.027778" Y="92.098765" S="1.000000" />
        </TLFLandmarkFile>
    </TLFLandmarkFiles>
</TLFDBLandmarks>
